settings_jc/__init__.py
settings_jc/defaults.py
settings_jc/encdec.py
settings_jc/export.py
settings_jc/settings.py
settings_jc-0.0.2.dist-info/LICENSE
settings_jc-0.0.2.dist-info/METADATA
settings_jc-0.0.2.dist-info/WHEEL
settings_jc-0.0.2.dist-info/top_level.txt
settings_jc-0.0.2.dist-info/RECORD
