Metadata-Version: 2.1
Name: settings-jc
Version: 0.0.2
Summary: Application Settings
Home-page: https://github.com/jcarter62/settings_jc.git
Author: Jim Carter
Author-email: jcarter62@gmail.com
License: UNKNOWN
Platform: UNKNOWN
Classifier: Programming Language :: Python :: 3
Classifier: License :: OSI Approved :: MIT License
Classifier: Operating System :: OS Independent
Requires-Python: >=3.6
Requires-Dist: cryptography
Requires-Dist: getmac
Requires-Dist: arrow
